kvargs.py
kvgargs.py
kvgargs-0.2.0.dist-info/LICENSE
kvgargs-0.2.0.dist-info/METADATA
kvgargs-0.2.0.dist-info/WHEEL
kvgargs-0.2.0.dist-info/top_level.txt
kvgargs-0.2.0.dist-info/RECORD
