Metadata-Version: 2.1
Name: kvgargs
Version: 0.2.0
Summary: Grouped key-value command line argument parser
Home-page: https://declassed.art/repository/kvgargs
Author: AXY
Author-email: axy@declassed.art
License: UNKNOWN
Platform: UNKNOWN
Classifier: Programming Language :: Python :: 3
Classifier: License :: OSI Approved :: BSD License
Classifier: Operating System :: OS Independent
Classifier: Intended Audience :: Developers
Classifier: Development Status :: 4 - Beta
Classifier: Topic :: Software Development :: User Interfaces
Requires-Python: >=3.6
